Metadata-Version: 2.4
Name: stylus-analyzer
Version: 0.1.12
Summary: AI-powered bug detection tool for Stylus/Rust contracts
Home-page: https://github.com/StylusAnalyzer/stylus-analyzer
Author: Jay Sojitra
Author-email: jaysojitra@lampros.tech
Keywords: stylus,rust,security,smart-contracts,analysis,ai
Classifier: Development Status :: 3 - Alpha
Classifier: Intended Audience :: Developers
Classifier: Topic :: Software Development :: Quality Assurance
Classifier: Programming Language :: Python :: 3
Classifier: Programming Language :: Python :: 3.8
Classifier: Programming Language :: Python :: 3.9
Classifier: Programming Language :: Python :: 3.10
Classifier: License :: OSI Approved :: MIT License
Requires-Python: >=3.8
License-File: LICENSE
Requires-Dist: openai>=1.0.0
Requires-Dist: python-dotenv>=1.0.0
Requires-Dist: click>=8.0.0
Requires-Dist: tree-sitter==0.20.2
Requires-Dist: setuptools>=42.0.0
Requires-Dist: reportlab>=3.0.0
Dynamic: author
Dynamic: author-email
Dynamic: classifier
Dynamic: description
Dynamic: description-content-type
Dynamic: home-page
Dynamic: keywords
Dynamic: license-file
Dynamic: requires-dist
Dynamic: requires-python
Dynamic: summary
